.gitignore
HISTORY.txt
MANIFEST.in
README.md
package.json
runtests.py
setup.py
class_backed_field/__init__.py
class_backed_field/fields.py
django_class_backed_field.egg-info/PKG-INFO
django_class_backed_field.egg-info/SOURCES.txt
django_class_backed_field.egg-info/dependency_links.txt
django_class_backed_field.egg-info/requires.txt
django_class_backed_field.egg-info/top_level.txt
tests/__init__.py
tests/models.py
tests/test.py