Metadata-Version: 1.1
Name: django-class-backed-field
Version: 0.1
Summary: This project has a field which extends a charfield and will pass the string stored in the database to the constructor of the object specified
Home-page: https://github.com/themotleyfool/django-class-backed-field
Author: Brian Faherty
Author-email: anothergenericuser@gmail.com
License: UNKNOWN
Platform: UNKNOWN
Classifier: Development Status :: 4 - Beta
Classifier: License :: OSI Approved :: BSD License
Classifier: Environment :: Web Environment
Classifier: Framework :: Django
Classifier: Intended Audience :: Developers
Classifier: Operating System :: OS Independent
Classifier: Programming Language :: Python
